paquetepruebaelirmviernes/__init__.py
paquetepruebaelirmviernes/resta.py
paquetepruebaelirmviernes/suma.py
paquetepruebaelirmviernes/extras/__init__.py
paquetepruebaelirmviernes/extras/divide.py
paquetepruebaelirmviernes/extras/multiplica.py
paquetepruebaelirmviernes-0.0.1.dist-info/METADATA
paquetepruebaelirmviernes-0.0.1.dist-info/WHEEL
paquetepruebaelirmviernes-0.0.1.dist-info/top_level.txt
paquetepruebaelirmviernes-0.0.1.dist-info/RECORD
