Metadata-Version: 2.1
Name: paquetepruebaelirmviernes
Version: 0.0.1
Summary: Mi primer paquete de Python
Author: Jason Dsouza
Author-email: <tuemail@email.com>
Keywords: python,primer paquete
Classifier: Development Status :: 3 - Alpha
Classifier: Intended Audience :: Education
Classifier: Programming Language :: Python :: 2
Classifier: Programming Language :: Python :: 3
Classifier: Operating System :: MacOS :: MacOS X
Classifier: Operating System :: Microsoft :: Windows
